<?xml version="1.0" encoding="UTF-8"?><TestSessionContainer xmlns="http://www.codecover.org/xml/testsession-container" Date="1441604088431" TestSessionContainerId="cc82c718-cbd6-4165-a35b-95c28286de3f" version="1.0">
<SrcFileList>
<SrcFile Content="//Interacts with the user&#10;&#10;package com.tw.biblioteca;&#10;&#10;import java.util.Scanner;&#10;&#10;public class View {&#10;&#10;    String message;&#10;&#10;    public View(String message) {&#10;&#10;        this.message = message;&#10;    }&#10;&#10;    public void displayMessage() {&#10;&#10;        System.out.println(message);&#10;    }&#10;&#10;    public String getInput() {&#10;        Scanner scanner = new Scanner(System.in);&#10;        return scanner.next();&#10;    }&#10;}&#10;" Filename="View.java" Intrnl_Id="1"/>
<SrcFile Content="//Tells the user to enter a valid menu option&#10;&#10;package com.tw.biblioteca;&#10;&#10;public class InvalidMenuItem implements MenuItem{&#10;&#10;    String errorMessage;&#10;    InvalidMenuItem() {&#10;        this.errorMessage = &quot;Select a valid option!&quot;;&#10;    }&#10;&#10;    public void execute() {&#10;        System.out.println(errorMessage);&#10;    }&#10;&#10;}&#10;" Filename="InvalidMenuItem.java" Intrnl_Id="2"/>
<SrcFile Content="package com.tw.biblioteca;&#10;&#10;public interface MenuItem {&#10;        public void execute();&#10;}&#10;" Filename="MenuItem.java" Intrnl_Id="3"/>
<SrcFile Content="//contains a menu list that can be displayed&#10;&#10;package com.tw.biblioteca;&#10;&#10;import java.util.ArrayList;&#10;&#10;public class Menu {&#10;    ArrayList&lt;String&gt; menu= new ArrayList&lt;String&gt;();&#10;    Menu() {&#10;        menu.add(&quot;1. List Books&quot;);&#10;        menu.add(&quot;2. Exit&quot;);&#10;    }&#10;&#10;    @Override&#10;    public String toString() {&#10;        StringBuilder stringBuilder = new StringBuilder();&#10;        stringBuilder.append(&quot;Menu\n&quot;);&#10;        for(String menuItem : menu){&#10;            stringBuilder.append(menuItem);&#10;        }&#10;        return stringBuilder.toString();&#10;    }&#10;}&#10;" Filename="Menu.java" Intrnl_Id="4"/>
<SrcFile Content="//Contains book details in a certain format&#10;&#10;package com.tw.biblioteca;&#10;&#10;public class Book {&#10;    private String name, author;&#10;    private int yearOfPublication;&#10;&#10;    public Book(String name, String author, int yearOfPublication) {&#10;        this.name = name;&#10;        this.author = author;&#10;        this. yearOfPublication = yearOfPublication;&#10;    }&#10;&#10;    @Override&#10;    public String toString() {&#10;&#10;        return (name+&quot;\t&quot;+author+&quot;\t&quot;+yearOfPublication);&#10;    }&#10;&#10;}&#10;" Filename="Book.java" Intrnl_Id="5"/>
<SrcFile Content="package com.tw.biblioteca;&#10;&#10;public class Application {&#10;    public static void main(String[] args) {&#10;        Application application = new Application();&#10;        application.start();&#10;    }&#10;&#10;    private void start() {&#10;        View view = new View(&quot;Welcome to Biblioteca&quot;);&#10;        view.displayMessage();&#10;&#10;        //while(true) {&#10;            Menu menu = new Menu();&#10;            view = new View(menu.toString());&#10;            view.displayMessage();&#10;            String input = view.getInput();&#10;            System.out.println(input);&#10;            //Parser parser = new Parser(input);&#10;            //MenuItem menuItem = parser.createMenuItem();&#10;            //menuItem.execute();&#10;        //}&#10;    }&#10;}&#10;" Filename="Application.java" Intrnl_Id="6"/>
<SrcFile Content="//Contains a list of books which can be displayed&#10;&#10;package com.tw.biblioteca;&#10;&#10;import java.util.ArrayList;&#10;&#10;public class Library implements MenuItem{&#10;&#10;    ArrayList&lt;Book&gt; booklist= new ArrayList&lt;Book&gt;();&#10;&#10;    Library(ArrayList&lt;Book&gt; booklist) {&#10;        this.booklist = booklist;&#10;    }&#10;&#10;&#10;    @Override&#10;    public void execute() {&#10;&#10;        StringBuilder stringBuilder = new StringBuilder();&#10;        stringBuilder.append(&quot;Name\tAuthor\tYear\n&quot;);&#10;&#10;        for(Book book : booklist) {&#10;            stringBuilder.append(book.toString()+&quot;\n&quot;);&#10;        }&#10;&#10;        System.out.print(stringBuilder.toString());&#10;    }&#10;}&#10;" Filename="Library.java" Intrnl_Id="7"/>
<SrcFile Content="//Exits the application&#10;&#10;package com.tw.biblioteca;&#10;&#10;public class Exit implements MenuItem{&#10;&#10;    @Override&#10;    public void execute() {&#10;        System.exit(0);&#10;    }&#10;}&#10;" Filename="Exit.java" Intrnl_Id="8"/>
<SrcFile Content="//Parses the menu option entered by the user&#10;&#10;package com.tw.biblioteca;&#10;&#10;import java.util.ArrayList;&#10;&#10;public class Parser {&#10;    private String option;&#10;&#10;    public Parser(String option) {&#10;        this.option = option;&#10;    }&#10;&#10;    public boolean isValid() {&#10;        if(option.matches(&quot;[0-9]+&quot;) &amp;&amp; convertOptionToInt() &gt; 0 &amp;&amp; convertOptionToInt() &lt;= 2 ) {&#10;            return true;&#10;        }&#10;        return false;&#10;    }&#10;&#10;    private int convertOptionToInt() {&#10;        return Integer.parseInt(option);&#10;    }&#10;&#10;    public MenuItem createMenuItem() {&#10;        if(isValid()) {&#10;            if (convertOptionToInt() == 1) {&#10;                ArrayList&lt;Book&gt; list = new ArrayList&lt;Book&gt;();&#10;                Book book1 = new Book(&quot;Harry Potter&quot;, &quot;J. K. Rowling&quot;, 1997);&#10;                Book book2 = new Book(&quot;Tale of Two Cities&quot;, &quot;Charles Dickens&quot;, 1859);&#10;                list.add(book1);&#10;                list.add(book2);&#10;                return new Library(list);&#10;            }&#10;            else if(convertOptionToInt() == 2) {&#10;                return new Exit();&#10;            }&#10;        }&#10;        return new InvalidMenuItem();&#10;    }&#10;}&#10;" Filename="Parser.java" Intrnl_Id="9"/>
</SrcFileList>
<CritList>
<CritListEntry Name="org.codecover.model.utils.criteria.LoopCoverage" PluginName="org.codecover"/>
<CritListEntry Name="org.codecover.model.utils.criteria.BranchCoverage" PluginName="org.codecover"/>
<CritListEntry Name="org.codecover.model.utils.criteria.ConditionCoverage" PluginName="org.codecover"/>
<CritListEntry Name="org.codecover.model.utils.criteria.StatementCoverage" PluginName="org.codecover"/>
</CritList>
<BoolOpList>
<BoolOp Arity="2" Intrnl_Id="10" Name="conditional and (&amp;&amp;)">
<BoolAssgnmntBoolMapList>
<MapEntry BoolAssgnmnt="10" Value="false"/>
<MapEntry BoolAssgnmnt="02" Value="false"/>
<MapEntry BoolAssgnmnt="11" Value="true"/>
</BoolAssgnmntBoolMapList>
</BoolOp>
</BoolOpList>
<HierarchyLvlTypeList>
<HierarchyLvlType EnglishName="package" IntrnlName="package" Intrnl_Id="11"/>
<HierarchyLvlType EnglishName="class" IntrnlName="class" Intrnl_Id="12"/>
<HierarchyLvlType EnglishName="method" IntrnlName="method" Intrnl_Id="13"/>
<HierarchyLvlType EnglishName="default package" IntrnlName="default package" Intrnl_Id="14"/>
<HierarchyLvlType EnglishName="interface" IntrnlName="interface" Intrnl_Id="15"/>
</HierarchyLvlTypeList>
<MASTRoot>
<HierarchyLvl HierarchyLvlId="32" HierarchyLvlTypeId="14" Intrnl_Id="16" Name="default package">
<Header/>
<LocList/>
<HierarchyLvl HierarchyLvlId="31" HierarchyLvlTypeId="11" Intrnl_Id="17" Name="com">
<Header/>
<LocList/>
<HierarchyLvl HierarchyLvlId="30" HierarchyLvlTypeId="11" Intrnl_Id="18" Name="tw">
<Header/>
<LocList/>
<HierarchyLvl HierarchyLvlId="29" HierarchyLvlTypeId="11" Intrnl_Id="19" Name="biblioteca">
<Header/>
<LocList/>
<HierarchyLvl HierarchyLvlId="4" HierarchyLvlTypeId="12" Intrnl_Id="20" Name="View">
<Header>
<Loc EndOffset="99" SrcFileId="1" StartOffset="82"/>
</Header>
<LocList>
<Loc EndOffset="397" SrcFileId="1" StartOffset="82"/>
</LocList>
<HierarchyLvl HierarchyLvlId="1" HierarchyLvlTypeId="13" Intrnl_Id="21" Name="View">
<Header>
<Loc EndOffset="155" SrcFileId="1" StartOffset="128"/>
</Header>
<LocList>
<Loc EndOffset="196" SrcFileId="1" StartOffset="128"/>
</LocList>
<StmntSeq Intrnl_Id="22">
<LocList>
<Loc EndOffset="190" SrcFileId="1" StartOffset="167"/>
</LocList>
<BasicStmnt CovItemId="S1" CovItemPrefix="com.tw.biblioteca.View.java" Intrnl_Id="23">
<LocList>
<Loc EndOffset="190" SrcFileId="1" StartOffset="167"/>
</LocList>
</BasicStmnt>
</StmntSeq>
</HierarchyLvl>
<HierarchyLvl HierarchyLvlId="2" HierarchyLvlTypeId="13" Intrnl_Id="24" Name="displayMessage">
<Header>
<Loc EndOffset="230" SrcFileId="1" StartOffset="202"/>
</Header>
<LocList>
<Loc EndOffset="276" SrcFileId="1" StartOffset="202"/>
</LocList>
<StmntSeq Intrnl_Id="25">
<LocList>
<Loc EndOffset="270" SrcFileId="1" StartOffset="242"/>
</LocList>
<BasicStmnt CovItemId="S2" CovItemPrefix="com.tw.biblioteca.View.java" Intrnl_Id="26">
<LocList>
<Loc EndOffset="270" SrcFileId="1" StartOffset="242"/>
</LocList>
</BasicStmnt>
</StmntSeq>
</HierarchyLvl>
<HierarchyLvl HierarchyLvlId="3" HierarchyLvlTypeId="13" Intrnl_Id="27" Name="getInput">
<Header>
<Loc EndOffset="306" SrcFileId="1" StartOffset="282"/>
</Header>
<LocList>
<Loc EndOffset="395" SrcFileId="1" StartOffset="282"/>
</LocList>
<StmntSeq Intrnl_Id="28">
<LocList>
<Loc EndOffset="358" SrcFileId="1" StartOffset="317"/>
</LocList>
<BasicStmnt CovItemId="S3" CovItemPrefix="com.tw.biblioteca.View.java" Intrnl_Id="29">
<LocList>
<Loc EndOffset="358" SrcFileId="1" StartOffset="317"/>
</LocList>
</BasicStmnt>
</StmntSeq>
</HierarchyLvl>
</HierarchyLvl>
<HierarchyLvl HierarchyLvlId="7" HierarchyLvlTypeId="12" Intrnl_Id="30" Name="InvalidMenuItem">
<Header>
<Loc EndOffset="123" SrcFileId="2" StartOffset="75"/>
</Header>
<LocList>
<Loc EndOffset="314" SrcFileId="2" StartOffset="75"/>
</LocList>
<HierarchyLvl HierarchyLvlId="5" HierarchyLvlTypeId="13" Intrnl_Id="31" Name="InvalidMenuItem">
<Header>
<Loc EndOffset="172" SrcFileId="2" StartOffset="155"/>
</Header>
<LocList>
<Loc EndOffset="234" SrcFileId="2" StartOffset="155"/>
</LocList>
<StmntSeq Intrnl_Id="32">
<LocList>
<Loc EndOffset="228" SrcFileId="2" StartOffset="183"/>
</LocList>
<BasicStmnt CovItemId="S1" CovItemPrefix="com.tw.biblioteca.InvalidMenuItem.java" Intrnl_Id="33">
<LocList>
<Loc EndOffset="228" SrcFileId="2" StartOffset="183"/>
</LocList>
</BasicStmnt>
</StmntSeq>
</HierarchyLvl>
<HierarchyLvl HierarchyLvlId="6" HierarchyLvlTypeId="13" Intrnl_Id="34" Name="execute">
<Header>
<Loc EndOffset="261" SrcFileId="2" StartOffset="240"/>
</Header>
<LocList>
<Loc EndOffset="311" SrcFileId="2" StartOffset="240"/>
</LocList>
<StmntSeq Intrnl_Id="35">
<LocList>
<Loc EndOffset="305" SrcFileId="2" StartOffset="272"/>
</LocList>
<BasicStmnt CovItemId="S2" CovItemPrefix="com.tw.biblioteca.InvalidMenuItem.java" Intrnl_Id="36">
<LocList>
<Loc EndOffset="305" SrcFileId="2" StartOffset="272"/>
</LocList>
</BasicStmnt>
</StmntSeq>
</HierarchyLvl>
</HierarchyLvl>
<HierarchyLvl HierarchyLvlId="9" HierarchyLvlTypeId="15" Intrnl_Id="37" Name="MenuItem">
<Header>
<Loc EndOffset="53" SrcFileId="3" StartOffset="28"/>
</Header>
<LocList>
<Loc EndOffset="88" SrcFileId="3" StartOffset="28"/>
</LocList>
<HierarchyLvl HierarchyLvlId="8" HierarchyLvlTypeId="13" Intrnl_Id="38" Name="execute">
<Header>
<Loc EndOffset="85" SrcFileId="3" StartOffset="64"/>
</Header>
<LocList>
<Loc EndOffset="86" SrcFileId="3" StartOffset="64"/>
</LocList>
</HierarchyLvl>
</HierarchyLvl>
<HierarchyLvl HierarchyLvlId="12" HierarchyLvlTypeId="12" Intrnl_Id="39" Name="Menu">
<Header>
<Loc EndOffset="120" SrcFileId="4" StartOffset="103"/>
</Header>
<LocList>
<Loc EndOffset="543" SrcFileId="4" StartOffset="103"/>
</LocList>
<StmntSeq Intrnl_Id="40">
<LocList>
<Loc EndOffset="175" SrcFileId="4" StartOffset="127"/>
</LocList>
<BasicStmnt CovItemId="S1" CovItemPrefix="com.tw.biblioteca.Menu.java" Intrnl_Id="41">
<LocList>
<Loc EndOffset="175" SrcFileId="4" StartOffset="127"/>
</LocList>
</BasicStmnt>
</StmntSeq>
<HierarchyLvl HierarchyLvlId="10" HierarchyLvlTypeId="13" Intrnl_Id="42" Name="Menu">
<Header>
<Loc EndOffset="186" SrcFileId="4" StartOffset="180"/>
</Header>
<LocList>
<Loc EndOffset="258" SrcFileId="4" StartOffset="180"/>
</LocList>
<StmntSeq Intrnl_Id="43">
<LocList>
<Loc EndOffset="223" SrcFileId="4" StartOffset="197"/>
<Loc EndOffset="252" SrcFileId="4" StartOffset="232"/>
</LocList>
<BasicStmnt CovItemId="S2" CovItemPrefix="com.tw.biblioteca.Menu.java" Intrnl_Id="44">
<LocList>
<Loc EndOffset="223" SrcFileId="4" StartOffset="197"/>
</LocList>
</BasicStmnt>
<BasicStmnt CovItemId="S3" CovItemPrefix="com.tw.biblioteca.Menu.java" Intrnl_Id="45">
<LocList>
<Loc EndOffset="252" SrcFileId="4" StartOffset="232"/>
</LocList>
</BasicStmnt>
</StmntSeq>
</HierarchyLvl>
<HierarchyLvl HierarchyLvlId="11" HierarchyLvlTypeId="13" Intrnl_Id="46" Name="toString">
<Header>
<Loc EndOffset="302" SrcFileId="4" StartOffset="264"/>
</Header>
<LocList>
<Loc EndOffset="541" SrcFileId="4" StartOffset="264"/>
</LocList>
<StmntSeq Intrnl_Id="47">
<LocList>
<Loc EndOffset="363" SrcFileId="4" StartOffset="313"/>
<Loc EndOffset="403" SrcFileId="4" StartOffset="372"/>
<Loc EndOffset="494" SrcFileId="4" StartOffset="412"/>
</LocList>
<BasicStmnt CovItemId="S4" CovItemPrefix="com.tw.biblioteca.Menu.java" Intrnl_Id="48">
<LocList>
<Loc EndOffset="363" SrcFileId="4" StartOffset="313"/>
</LocList>
</BasicStmnt>
<BasicStmnt CovItemId="S5" CovItemPrefix="com.tw.biblioteca.Menu.java" Intrnl_Id="49">
<LocList>
<Loc EndOffset="403" SrcFileId="4" StartOffset="372"/>
</LocList>
</BasicStmnt>
<LoopStmnt CovItemId="S6" CovItemPrefix="com.tw.biblioteca.Menu.java" Intrnl_Id="50" MltplExecId="L1-2" MltplExecPrefix="com.tw.biblioteca.Menu.java" NvrExecId="L1-0" NvrExecPrefix="com.tw.biblioteca.Menu.java" OnceExecutedId="L1-1" OnceExecutedPrefix="com.tw.biblioteca.Menu.java" OptBodyExec="true">
<StmntSeq Intrnl_Id="51">
<LocList>
<Loc EndOffset="484" SrcFileId="4" StartOffset="453"/>
</LocList>
<BasicStmnt CovItemId="S7" CovItemPrefix="com.tw.biblioteca.Menu.java" Intrnl_Id="52">
<LocList>
<Loc EndOffset="484" SrcFileId="4" StartOffset="453"/>
</LocList>
</BasicStmnt>
</StmntSeq>
<Keyword EndOffset="415" SrcFileId="4" StartOffset="412"/>
<LocList>
<Loc EndOffset="494" SrcFileId="4" StartOffset="412"/>
</LocList>
</LoopStmnt>
</StmntSeq>
</HierarchyLvl>
</HierarchyLvl>
<HierarchyLvl HierarchyLvlId="15" HierarchyLvlTypeId="12" Intrnl_Id="53" Name="Book">
<Header>
<Loc EndOffset="90" SrcFileId="5" StartOffset="73"/>
</Header>
<LocList>
<Loc EndOffset="459" SrcFileId="5" StartOffset="73"/>
</LocList>
<HierarchyLvl HierarchyLvlId="13" HierarchyLvlTypeId="13" Intrnl_Id="54" Name="Book">
<Header>
<Loc EndOffset="228" SrcFileId="5" StartOffset="166"/>
</Header>
<LocList>
<Loc EndOffset="345" SrcFileId="5" StartOffset="166"/>
</LocList>
<StmntSeq Intrnl_Id="55">
<LocList>
<Loc EndOffset="256" SrcFileId="5" StartOffset="239"/>
<Loc EndOffset="286" SrcFileId="5" StartOffset="265"/>
<Loc EndOffset="339" SrcFileId="5" StartOffset="295"/>
</LocList>
<BasicStmnt CovItemId="S1" CovItemPrefix="com.tw.biblioteca.Book.java" Intrnl_Id="56">
<LocList>
<Loc EndOffset="256" SrcFileId="5" StartOffset="239"/>
</LocList>
</BasicStmnt>
<BasicStmnt CovItemId="S2" CovItemPrefix="com.tw.biblioteca.Book.java" Intrnl_Id="57">
<LocList>
<Loc EndOffset="286" SrcFileId="5" StartOffset="265"/>
</LocList>
</BasicStmnt>
<BasicStmnt CovItemId="S3" CovItemPrefix="com.tw.biblioteca.Book.java" Intrnl_Id="58">
<LocList>
<Loc EndOffset="339" SrcFileId="5" StartOffset="295"/>
</LocList>
</BasicStmnt>
</StmntSeq>
</HierarchyLvl>
<HierarchyLvl HierarchyLvlId="14" HierarchyLvlTypeId="13" Intrnl_Id="59" Name="toString">
<Header>
<Loc EndOffset="389" SrcFileId="5" StartOffset="351"/>
</Header>
<LocList>
<Loc EndOffset="456" SrcFileId="5" StartOffset="351"/>
</LocList>
</HierarchyLvl>
</HierarchyLvl>
<HierarchyLvl HierarchyLvlId="18" HierarchyLvlTypeId="12" Intrnl_Id="60" Name="Application">
<Header>
<Loc EndOffset="52" SrcFileId="6" StartOffset="28"/>
</Header>
<LocList>
<Loc EndOffset="688" SrcFileId="6" StartOffset="28"/>
</LocList>
<HierarchyLvl HierarchyLvlId="16" HierarchyLvlTypeId="13" Intrnl_Id="61" Name="main">
<Header>
<Loc EndOffset="97" SrcFileId="6" StartOffset="59"/>
</Header>
<LocList>
<Loc EndOffset="187" SrcFileId="6" StartOffset="59"/>
</LocList>
<StmntSeq Intrnl_Id="62">
<LocList>
<Loc EndOffset="152" SrcFileId="6" StartOffset="108"/>
<Loc EndOffset="181" SrcFileId="6" StartOffset="161"/>
</LocList>
<BasicStmnt CovItemId="S1" CovItemPrefix="com.tw.biblioteca.Application.java" Intrnl_Id="63">
<LocList>
<Loc EndOffset="152" SrcFileId="6" StartOffset="108"/>
</LocList>
</BasicStmnt>
<BasicStmnt CovItemId="S2" CovItemPrefix="com.tw.biblioteca.Application.java" Intrnl_Id="64">
<LocList>
<Loc EndOffset="181" SrcFileId="6" StartOffset="161"/>
</LocList>
</BasicStmnt>
</StmntSeq>
</HierarchyLvl>
<HierarchyLvl HierarchyLvlId="17" HierarchyLvlTypeId="13" Intrnl_Id="65" Name="start">
<Header>
<Loc EndOffset="213" SrcFileId="6" StartOffset="193"/>
</Header>
<LocList>
<Loc EndOffset="686" SrcFileId="6" StartOffset="193"/>
</LocList>
<StmntSeq Intrnl_Id="66">
<LocList>
<Loc EndOffset="270" SrcFileId="6" StartOffset="224"/>
<Loc EndOffset="301" SrcFileId="6" StartOffset="279"/>
<Loc EndOffset="362" SrcFileId="6" StartOffset="339"/>
<Loc EndOffset="408" SrcFileId="6" StartOffset="375"/>
<Loc EndOffset="443" SrcFileId="6" StartOffset="421"/>
<Loc EndOffset="487" SrcFileId="6" StartOffset="456"/>
<Loc EndOffset="526" SrcFileId="6" StartOffset="500"/>
</LocList>
<BasicStmnt CovItemId="S3" CovItemPrefix="com.tw.biblioteca.Application.java" Intrnl_Id="67">
<LocList>
<Loc EndOffset="270" SrcFileId="6" StartOffset="224"/>
</LocList>
</BasicStmnt>
<BasicStmnt CovItemId="S4" CovItemPrefix="com.tw.biblioteca.Application.java" Intrnl_Id="68">
<LocList>
<Loc EndOffset="301" SrcFileId="6" StartOffset="279"/>
</LocList>
</BasicStmnt>
<BasicStmnt CovItemId="S5" CovItemPrefix="com.tw.biblioteca.Application.java" Intrnl_Id="69">
<LocList>
<Loc EndOffset="362" SrcFileId="6" StartOffset="339"/>
</LocList>
</BasicStmnt>
<BasicStmnt CovItemId="S6" CovItemPrefix="com.tw.biblioteca.Application.java" Intrnl_Id="70">
<LocList>
<Loc EndOffset="408" SrcFileId="6" StartOffset="375"/>
</LocList>
</BasicStmnt>
<BasicStmnt CovItemId="S7" CovItemPrefix="com.tw.biblioteca.Application.java" Intrnl_Id="71">
<LocList>
<Loc EndOffset="443" SrcFileId="6" StartOffset="421"/>
</LocList>
</BasicStmnt>
<BasicStmnt CovItemId="S8" CovItemPrefix="com.tw.biblioteca.Application.java" Intrnl_Id="72">
<LocList>
<Loc EndOffset="487" SrcFileId="6" StartOffset="456"/>
</LocList>
</BasicStmnt>
<BasicStmnt CovItemId="S9" CovItemPrefix="com.tw.biblioteca.Application.java" Intrnl_Id="73">
<LocList>
<Loc EndOffset="526" SrcFileId="6" StartOffset="500"/>
</LocList>
</BasicStmnt>
</StmntSeq>
</HierarchyLvl>
</HierarchyLvl>
<HierarchyLvl HierarchyLvlId="21" HierarchyLvlTypeId="12" Intrnl_Id="74" Name="Library">
<Header>
<Loc EndOffset="148" SrcFileId="7" StartOffset="108"/>
</Header>
<LocList>
<Loc EndOffset="606" SrcFileId="7" StartOffset="108"/>
</LocList>
<StmntSeq Intrnl_Id="75">
<LocList>
<Loc EndOffset="203" SrcFileId="7" StartOffset="155"/>
</LocList>
<BasicStmnt CovItemId="S1" CovItemPrefix="com.tw.biblioteca.Library.java" Intrnl_Id="76">
<LocList>
<Loc EndOffset="203" SrcFileId="7" StartOffset="155"/>
</LocList>
</BasicStmnt>
</StmntSeq>
<HierarchyLvl HierarchyLvlId="19" HierarchyLvlTypeId="13" Intrnl_Id="77" Name="Library">
<Header>
<Loc EndOffset="242" SrcFileId="7" StartOffset="209"/>
</Header>
<LocList>
<Loc EndOffset="284" SrcFileId="7" StartOffset="209"/>
</LocList>
<StmntSeq Intrnl_Id="78">
<LocList>
<Loc EndOffset="278" SrcFileId="7" StartOffset="253"/>
</LocList>
<BasicStmnt CovItemId="S2" CovItemPrefix="com.tw.biblioteca.Library.java" Intrnl_Id="79">
<LocList>
<Loc EndOffset="278" SrcFileId="7" StartOffset="253"/>
</LocList>
</BasicStmnt>
</StmntSeq>
</HierarchyLvl>
<HierarchyLvl HierarchyLvlId="20" HierarchyLvlTypeId="13" Intrnl_Id="80" Name="execute">
<Header>
<Loc EndOffset="326" SrcFileId="7" StartOffset="291"/>
</Header>
<LocList>
<Loc EndOffset="604" SrcFileId="7" StartOffset="291"/>
</LocList>
<StmntSeq Intrnl_Id="81">
<LocList>
<Loc EndOffset="388" SrcFileId="7" StartOffset="338"/>
<Loc EndOffset="442" SrcFileId="7" StartOffset="397"/>
<Loc EndOffset="545" SrcFileId="7" StartOffset="452"/>
<Loc EndOffset="598" SrcFileId="7" StartOffset="555"/>
</LocList>
<BasicStmnt CovItemId="S3" CovItemPrefix="com.tw.biblioteca.Library.java" Intrnl_Id="82">
<LocList>
<Loc EndOffset="388" SrcFileId="7" StartOffset="338"/>
</LocList>
</BasicStmnt>
<BasicStmnt CovItemId="S4" CovItemPrefix="com.tw.biblioteca.Library.java" Intrnl_Id="83">
<LocList>
<Loc EndOffset="442" SrcFileId="7" StartOffset="397"/>
</LocList>
</BasicStmnt>
<LoopStmnt CovItemId="S5" CovItemPrefix="com.tw.biblioteca.Library.java" Intrnl_Id="84" MltplExecId="L1-2" MltplExecPrefix="com.tw.biblioteca.Library.java" NvrExecId="L1-0" NvrExecPrefix="com.tw.biblioteca.Library.java" OnceExecutedId="L1-1" OnceExecutedPrefix="com.tw.biblioteca.Library.java" OptBodyExec="true">
<StmntSeq Intrnl_Id="85">
<LocList>
<Loc EndOffset="535" SrcFileId="7" StartOffset="492"/>
</LocList>
<BasicStmnt CovItemId="S6" CovItemPrefix="com.tw.biblioteca.Library.java" Intrnl_Id="86">
<LocList>
<Loc EndOffset="535" SrcFileId="7" StartOffset="492"/>
</LocList>
</BasicStmnt>
</StmntSeq>
<Keyword EndOffset="455" SrcFileId="7" StartOffset="452"/>
<LocList>
<Loc EndOffset="545" SrcFileId="7" StartOffset="452"/>
</LocList>
</LoopStmnt>
<BasicStmnt CovItemId="S7" CovItemPrefix="com.tw.biblioteca.Library.java" Intrnl_Id="87">
<LocList>
<Loc EndOffset="598" SrcFileId="7" StartOffset="555"/>
</LocList>
</BasicStmnt>
</StmntSeq>
</HierarchyLvl>
</HierarchyLvl>
<HierarchyLvl HierarchyLvlId="23" HierarchyLvlTypeId="12" Intrnl_Id="88" Name="Exit">
<Header>
<Loc EndOffset="90" SrcFileId="8" StartOffset="53"/>
</Header>
<LocList>
<Loc EndOffset="166" SrcFileId="8" StartOffset="53"/>
</LocList>
<HierarchyLvl HierarchyLvlId="22" HierarchyLvlTypeId="13" Intrnl_Id="89" Name="execute">
<Header>
<Loc EndOffset="132" SrcFileId="8" StartOffset="97"/>
</Header>
<LocList>
<Loc EndOffset="164" SrcFileId="8" StartOffset="97"/>
</LocList>
<StmntSeq Intrnl_Id="90">
<LocList>
<Loc EndOffset="158" SrcFileId="8" StartOffset="143"/>
</LocList>
<BasicStmnt CovItemId="S1" CovItemPrefix="com.tw.biblioteca.Exit.java" Intrnl_Id="91">
<LocList>
<Loc EndOffset="158" SrcFileId="8" StartOffset="143"/>
</LocList>
</BasicStmnt>
</StmntSeq>
</HierarchyLvl>
</HierarchyLvl>
<HierarchyLvl HierarchyLvlId="28" HierarchyLvlTypeId="12" Intrnl_Id="92" Name="Parser">
<Header>
<Loc EndOffset="122" SrcFileId="9" StartOffset="103"/>
</Header>
<LocList>
<Loc EndOffset="1113" SrcFileId="9" StartOffset="103"/>
</LocList>
<HierarchyLvl HierarchyLvlId="24" HierarchyLvlTypeId="13" Intrnl_Id="93" Name="Parser">
<Header>
<Loc EndOffset="185" SrcFileId="9" StartOffset="157"/>
</Header>
<LocList>
<Loc EndOffset="223" SrcFileId="9" StartOffset="157"/>
</LocList>
<StmntSeq Intrnl_Id="94">
<LocList>
<Loc EndOffset="217" SrcFileId="9" StartOffset="196"/>
</LocList>
<BasicStmnt CovItemId="S1" CovItemPrefix="com.tw.biblioteca.Parser.java" Intrnl_Id="95">
<LocList>
<Loc EndOffset="217" SrcFileId="9" StartOffset="196"/>
</LocList>
</BasicStmnt>
</StmntSeq>
</HierarchyLvl>
<HierarchyLvl HierarchyLvlId="25" HierarchyLvlTypeId="13" Intrnl_Id="96" Name="isValid">
<Header>
<Loc EndOffset="253" SrcFileId="9" StartOffset="229"/>
</Header>
<LocList>
<Loc EndOffset="415" SrcFileId="9" StartOffset="229"/>
</LocList>
<StmntSeq Intrnl_Id="97">
<LocList>
<Loc EndOffset="387" SrcFileId="9" StartOffset="264"/>
</LocList>
<CondStmnt CovItemId="S2" CovItemPrefix="com.tw.biblioteca.Parser.java" Intrnl_Id="98">
<Branch CovItemId="B1" CovItemPrefix="com.tw.biblioteca.Parser.java" Implct="false" Intrnl_Id="99">
<Cond/>
<LocList>
<Loc EndOffset="387" SrcFileId="9" StartOffset="351"/>
</LocList>
<StmntSeq Intrnl_Id="100">
<LocList/>
</StmntSeq>
</Branch>
<Branch CovItemId="B2" CovItemPrefix="com.tw.biblioteca.Parser.java" Implct="true" Intrnl_Id="101">
<Cond/>
<LocList/>
<StmntSeq Intrnl_Id="102">
<LocList/>
</StmntSeq>
</Branch>
<Keyword EndOffset="266" SrcFileId="9" StartOffset="264"/>
<LocList>
<Loc EndOffset="387" SrcFileId="9" StartOffset="264"/>
</LocList>
<RootTerm CovItemId="C1" CovItemPrefix="com.tw.biblioteca.Parser.java" Intrnl_Id="103">
<OpTerm BooleanOpId="10" Intrnl_Id="104">
<OpTerm BooleanOpId="10" Intrnl_Id="105">
<BasicBoolTerm Intrnl_Id="106">
<LocList>
<Loc EndOffset="291" SrcFileId="9" StartOffset="267"/>
</LocList>
</BasicBoolTerm>
<BasicBoolTerm Intrnl_Id="107">
<LocList>
<Loc EndOffset="319" SrcFileId="9" StartOffset="295"/>
</LocList>
</BasicBoolTerm>
<LocList>
<Loc EndOffset="294" SrcFileId="9" StartOffset="292"/>
</LocList>
</OpTerm>
<BasicBoolTerm Intrnl_Id="108">
<LocList>
<Loc EndOffset="348" SrcFileId="9" StartOffset="323"/>
</LocList>
</BasicBoolTerm>
<LocList>
<Loc EndOffset="322" SrcFileId="9" StartOffset="320"/>
</LocList>
</OpTerm>
</RootTerm>
</CondStmnt>
</StmntSeq>
</HierarchyLvl>
<HierarchyLvl HierarchyLvlId="26" HierarchyLvlTypeId="13" Intrnl_Id="109" Name="convertOptionToInt">
<Header>
<Loc EndOffset="453" SrcFileId="9" StartOffset="421"/>
</Header>
<LocList>
<Loc EndOffset="502" SrcFileId="9" StartOffset="421"/>
</LocList>
</HierarchyLvl>
<HierarchyLvl HierarchyLvlId="27" HierarchyLvlTypeId="13" Intrnl_Id="110" Name="createMenuItem">
<Header>
<Loc EndOffset="540" SrcFileId="9" StartOffset="508"/>
</Header>
<LocList>
<Loc EndOffset="1111" SrcFileId="9" StartOffset="508"/>
</LocList>
<StmntSeq Intrnl_Id="111">
<LocList>
<Loc EndOffset="1067" SrcFileId="9" StartOffset="551"/>
</LocList>
<CondStmnt CovItemId="S3" CovItemPrefix="com.tw.biblioteca.Parser.java" Intrnl_Id="112">
<Branch CovItemId="B3" CovItemPrefix="com.tw.biblioteca.Parser.java" Implct="false" Intrnl_Id="113">
<Cond/>
<LocList>
<Loc EndOffset="1067" SrcFileId="9" StartOffset="565"/>
</LocList>
<StmntSeq Intrnl_Id="114">
<LocList>
<Loc EndOffset="1057" SrcFileId="9" StartOffset="579"/>
</LocList>
<CondStmnt CovItemId="S4" CovItemPrefix="com.tw.biblioteca.Parser.java" Intrnl_Id="115">
<Branch CovItemId="B5" CovItemPrefix="com.tw.biblioteca.Parser.java" Implct="false" Intrnl_Id="116">
<Cond/>
<LocList>
<Loc EndOffset="959" SrcFileId="9" StartOffset="610"/>
</LocList>
<StmntSeq Intrnl_Id="117">
<LocList>
<Loc EndOffset="673" SrcFileId="9" StartOffset="628"/>
<Loc EndOffset="751" SrcFileId="9" StartOffset="690"/>
<Loc EndOffset="837" SrcFileId="9" StartOffset="768"/>
<Loc EndOffset="870" SrcFileId="9" StartOffset="854"/>
<Loc EndOffset="903" SrcFileId="9" StartOffset="887"/>
</LocList>
<BasicStmnt CovItemId="S5" CovItemPrefix="com.tw.biblioteca.Parser.java" Intrnl_Id="118">
<LocList>
<Loc EndOffset="673" SrcFileId="9" StartOffset="628"/>
</LocList>
</BasicStmnt>
<BasicStmnt CovItemId="S6" CovItemPrefix="com.tw.biblioteca.Parser.java" Intrnl_Id="119">
<LocList>
<Loc EndOffset="751" SrcFileId="9" StartOffset="690"/>
</LocList>
</BasicStmnt>
<BasicStmnt CovItemId="S7" CovItemPrefix="com.tw.biblioteca.Parser.java" Intrnl_Id="120">
<LocList>
<Loc EndOffset="837" SrcFileId="9" StartOffset="768"/>
</LocList>
</BasicStmnt>
<BasicStmnt CovItemId="S8" CovItemPrefix="com.tw.biblioteca.Parser.java" Intrnl_Id="121">
<LocList>
<Loc EndOffset="870" SrcFileId="9" StartOffset="854"/>
</LocList>
</BasicStmnt>
<BasicStmnt CovItemId="S9" CovItemPrefix="com.tw.biblioteca.Parser.java" Intrnl_Id="122">
<LocList>
<Loc EndOffset="903" SrcFileId="9" StartOffset="887"/>
</LocList>
</BasicStmnt>
</StmntSeq>
</Branch>
<Branch CovItemId="B6" CovItemPrefix="com.tw.biblioteca.Parser.java" Implct="false" Intrnl_Id="123">
<Cond>
<Loc EndOffset="976" SrcFileId="9" StartOffset="972"/>
</Cond>
<LocList>
<Loc EndOffset="1057" SrcFileId="9" StartOffset="977"/>
</LocList>
<StmntSeq Intrnl_Id="124">
<LocList>
<Loc EndOffset="1057" SrcFileId="9" StartOffset="977"/>
</LocList>
<CondStmnt CovItemId="S10" CovItemPrefix="com.tw.biblioteca.Parser.java" Intrnl_Id="125">
<Branch CovItemId="B7" CovItemPrefix="com.tw.biblioteca.Parser.java" Implct="false" Intrnl_Id="126">
<Cond/>
<LocList>
<Loc EndOffset="1057" SrcFileId="9" StartOffset="1007"/>
</LocList>
<StmntSeq Intrnl_Id="127">
<LocList/>
</StmntSeq>
</Branch>
<Branch CovItemId="B8" CovItemPrefix="com.tw.biblioteca.Parser.java" Implct="true" Intrnl_Id="128">
<Cond/>
<LocList/>
<StmntSeq Intrnl_Id="129">
<LocList/>
</StmntSeq>
</Branch>
<Keyword EndOffset="979" SrcFileId="9" StartOffset="977"/>
<LocList>
<Loc EndOffset="1057" SrcFileId="9" StartOffset="977"/>
</LocList>
<RootTerm CovItemId="C4" CovItemPrefix="com.tw.biblioteca.Parser.java" Intrnl_Id="130">
<BasicBoolTerm Intrnl_Id="131">
<LocList>
<Loc EndOffset="1005" SrcFileId="9" StartOffset="980"/>
</LocList>
</BasicBoolTerm>
</RootTerm>
</CondStmnt>
</StmntSeq>
</Branch>
<Keyword EndOffset="581" SrcFileId="9" StartOffset="579"/>
<LocList>
<Loc EndOffset="1057" SrcFileId="9" StartOffset="579"/>
</LocList>
<RootTerm CovItemId="C3" CovItemPrefix="com.tw.biblioteca.Parser.java" Intrnl_Id="132">
<BasicBoolTerm Intrnl_Id="133">
<LocList>
<Loc EndOffset="608" SrcFileId="9" StartOffset="583"/>
</LocList>
</BasicBoolTerm>
</RootTerm>
</CondStmnt>
</StmntSeq>
</Branch>
<Branch CovItemId="B4" CovItemPrefix="com.tw.biblioteca.Parser.java" Implct="true" Intrnl_Id="134">
<Cond/>
<LocList/>
<StmntSeq Intrnl_Id="135">
<LocList/>
</StmntSeq>
</Branch>
<Keyword EndOffset="553" SrcFileId="9" StartOffset="551"/>
<LocList>
<Loc EndOffset="1067" SrcFileId="9" StartOffset="551"/>
</LocList>
<RootTerm CovItemId="C2" CovItemPrefix="com.tw.biblioteca.Parser.java" Intrnl_Id="136">
<BasicBoolTerm Intrnl_Id="137">
<LocList>
<Loc EndOffset="563" SrcFileId="9" StartOffset="554"/>
</LocList>
</BasicBoolTerm>
</RootTerm>
</CondStmnt>
</StmntSeq>
</HierarchyLvl>
</HierarchyLvl>
</HierarchyLvl>
</HierarchyLvl>
</HierarchyLvl>
</HierarchyLvl>
</MASTRoot>
</TestSessionContainer>
